mltrace/__init__.py
mltrace/client.py
mltrace/utils.py
mltrace/cli/__init__.py
mltrace/cli/cli.py
mltrace/db/__init__.py
mltrace/db/base.py
mltrace/db/models.py
mltrace/db/store.py
mltrace/db/utils.py
mltrace/entities/__init__.py
mltrace/entities/base.py
mltrace/entities/base_component.py
mltrace/entities/base_test.py
mltrace/entities/component.py
mltrace/entities/component_run.py
mltrace/entities/components.py
mltrace/entities/io_pointer.py
mltrace/entities/tests.py
mltrace/entities/utils.py
mltrace/server/__init__.py
mltrace/server/manage.py
mltrace-0.17.dist-info/LICENSE
mltrace-0.17.dist-info/METADATA
mltrace-0.17.dist-info/WHEEL
mltrace-0.17.dist-info/entry_points.txt
mltrace-0.17.dist-info/top_level.txt
mltrace-0.17.dist-info/RECORD
