Metadata-Version: 2.1
Name: mltrace
Version: 0.17
Summary: Lineage and tracing for ML pipelines
Home-page: UNKNOWN
Author: shreyashankar
Author-email: shreya@cs.stanford.edu
License: Apache License 2.0
Project-URL: Bug Tracker, https://github.com/loglabs/mltrace/issues
Project-URL: Source Code, https://github.com/loglabs/mltrace
Platform: UNKNOWN
Classifier: Intended Audience :: Developers
Classifier: Programming Language :: Python
Classifier: Topic :: Software Development :: Bug Tracking
Requires-Dist: alembic
Requires-Dist: click
Requires-Dist: docker
Requires-Dist: flask
Requires-Dist: furo
Requires-Dist: gitpython
Requires-Dist: psycopg2-binary
Requires-Dist: pytest
Requires-Dist: python-dotenv
Requires-Dist: sqlalchemy
